kalmax/__init__.py
kalmax/demo_utils.py
kalmax/kalman.py
kalmax/kde.py
kalmax/kernels.py
kalmax/utils.py
kalmax-0.0.0.dist-info/LICENSE
kalmax-0.0.0.dist-info/METADATA
kalmax-0.0.0.dist-info/WHEEL
kalmax-0.0.0.dist-info/top_level.txt
kalmax-0.0.0.dist-info/RECORD
