Metadata-Version: 2.1
Name: kalmax
Version: 0.0.0
Summary: Kalman based neural decoding in Jax
Home-page: https://github.com/TomGeorge1234/KalMax
Author: Tom George
Classifier: Programming Language :: Python :: 3
Classifier: License :: OSI Approved :: MIT License
Classifier: Operating System :: OS Independent
Requires-Python: >=3.6
License-File: LICENSE
Requires-Dist: jax
Provides-Extra: demo
Requires-Dist: matplotlib ; extra == 'demo'
Requires-Dist: tqdm ; extra == 'demo'
Requires-Dist: ratinabox ; extra == 'demo'
Requires-Dist: pykalman ; extra == 'demo'
